lib_dzne_filedata/__init__.py
lib_dzne_filedata-0.5.2.dist-info/LICENSE.txt
lib_dzne_filedata-0.5.2.dist-info/METADATA
lib_dzne_filedata-0.5.2.dist-info/WHEEL
lib_dzne_filedata-0.5.2.dist-info/top_level.txt
lib_dzne_filedata-0.5.2.dist-info/RECORD
