Metadata-Version: 2.1
Name: lib-dzne-filedata
Version: 0.5.2
Summary: Libary for filedata handling. 
Author-email: Johannes <johannes-programming@posteo.org>
License: Copyright © 2022 Johannes Horler
Project-URL: Download, https://pypi.org/project/lib-dzne-filedata/#files
Project-URL: Source, https://github.com/johannes-programming/lib_dzne_filedata
Classifier: License :: OSI Approved :: MIT License
Classifier: Programming Language :: Python
Classifier: Programming Language :: Python :: 3
Requires-Python: >=3.11
License-File: LICENSE.txt
Requires-Dist: tomli-w >=1.0.0
Requires-Dist: lib-dzne-math >=0.2.3
